depthai_viewer/__init__.py
depthai_viewer/__main__.py
depthai_viewer/color_conversion.py
depthai_viewer/install_requirements.py
depthai_viewer/py.typed
depthai_viewer/recording.py
depthai_viewer/requirements.txt
depthai_viewer/script_helpers.py
depthai_viewer/_backend/.gitignore
depthai_viewer/_backend/README.md
depthai_viewer/_backend/__init__.py
depthai_viewer/_backend/classification_labels.py
depthai_viewer/_backend/config_api.py
depthai_viewer/_backend/depth.py
depthai_viewer/_backend/device.py
depthai_viewer/_backend/device_configuration.py
depthai_viewer/_backend/main.py
depthai_viewer/_backend/messages.py
depthai_viewer/_backend/packet_handler.py
depthai_viewer/_backend/py.typed
depthai_viewer/_backend/store.py
depthai_viewer/_backend/topic.py
depthai_viewer/_backend/device_defaults/oak_d_generic_default.py
depthai_viewer/_backend/device_defaults/oak_d_lr_default.py
depthai_viewer/_backend/device_defaults/oak_d_sr_default.py
depthai_viewer/_backend/device_defaults/oak_d_sr_poe_default.py
depthai_viewer/_backend/device_defaults/oak_t_default.py
depthai_viewer/components/__init__.py
depthai_viewer/components/annotation.py
depthai_viewer/components/arrow.py
depthai_viewer/components/box.py
depthai_viewer/components/color.py
depthai_viewer/components/imu.py
depthai_viewer/components/instance.py
depthai_viewer/components/label.py
depthai_viewer/components/linestrip.py
depthai_viewer/components/point.py
depthai_viewer/components/quaternion.py
depthai_viewer/components/radius.py
depthai_viewer/components/rect2d.py
depthai_viewer/components/scalar.py
depthai_viewer/components/tensor.py
depthai_viewer/components/text_entry.py
depthai_viewer/components/vec.py
depthai_viewer/components/xlink_stats.py
depthai_viewer/log/__init__.py
depthai_viewer/log/annotation.py
depthai_viewer/log/arrow.py
depthai_viewer/log/bounding_box.py
depthai_viewer/log/camera.py
depthai_viewer/log/error_utils.py
depthai_viewer/log/extension_components.py
depthai_viewer/log/file.py
depthai_viewer-0.2.8.dist-info/METADATA
depthai_viewer-0.2.8.dist-info/WHEEL
depthai_viewer-0.2.8.dist-info/entry_points.txt
depthai_viewer-0.2.8.dist-info/RECORD
