Metadata-Version: 2.1
Name: depthai-viewer
Version: 0.2.8
Classifier: Programming Language :: Rust
Classifier: Programming Language :: Python :: Implementation :: CPython
Classifier: Programming Language :: Python :: Implementation :: PyPy
Classifier: Development Status :: 3 - Alpha
Classifier: Topic :: Scientific/Engineering :: Artificial Intelligence
Classifier: Topic :: Scientific/Engineering :: Visualization
Requires-Dist: deprecated
Requires-Dist: numpy>=1.23
Requires-Dist: pyarrow==16.0.0
Requires-Dist: setuptools
Requires-Dist: pytest==7.1.2; extra == 'tests'
Provides-Extra: tests
Summary: Depthai Viewer
Keywords: computer-vision,logging,depthai-viewer
Author-email: Luxonis <filip.jeretina@luxonis.com>
License: MIT OR Apache-2.0
Requires-Python: >=3.8
Project-URL: repository, https://github.com/luxonis/depthai-viewer
Project-URL: documentation, https://www.rerun.io/docs
Project-URL: homepage, https://www.rerun.io
